beez/BeezUtils.py
beez/Types.py
beez/__init__.py
beez/version.py
beez/api/NodeAPI.py
beez/api/__init__.py
beez/block/Block.py
beez/block/Blockchain.py
beez/block/__init__.py
beez/consensus/Lot.py
beez/consensus/ProofOfStake.py
beez/consensus/__init__.py
beez/node/Node.py
beez/node/__init__.py
beez/socket/Message.py
beez/socket/MessageType.py
beez/socket/PeerDiscoveryHandler.py
beez/socket/SocketCommunication.py
beez/socket/SocketConnector.py
beez/socket/__init__.py
beez/state/AccountStateModel.py
beez/state/__init__.py
beez/transaction/Transaction.py
beez/transaction/TransactionPool.py
beez/transaction/TransactionType.py
beez/transaction/__init__.py
beez/wallet/Wallet.py
beez/wallet/__init__.py
beez-0.0.1.dist-info/LICENSE
beez-0.0.1.dist-info/METADATA
beez-0.0.1.dist-info/WHEEL
beez-0.0.1.dist-info/top_level.txt
beez-0.0.1.dist-info/RECORD
