Metadata-Version: 2.1
Name: beez
Version: 0.0.1
Summary: A Blockchain for Machine Learnig models and Digital Asset Management
Author: Enrico Zanardo
Author-email: enrico.zanardo101@gmail.com
License: UNKNOWN
Platform: UNKNOWN
Requires-Python: >=3.10.0
License-File: LICENSE
Requires-Dist: attrs (==21.4.0)
Requires-Dist: certifi (==2021.10.8)
Requires-Dist: charset-normalizer (==2.0.12)
Requires-Dist: click (==8.0.4)
Requires-Dist: flask (==2.0.3)
Requires-Dist: flask-classful (==0.14.2)
Requires-Dist: idna (==3.3)
Requires-Dist: iniconfig (==1.1.1)
Requires-Dist: itsdangerous (==2.1.1)
Requires-Dist: jinja2 (==3.0.3)
Requires-Dist: jsonpickle (==2.1.0)
Requires-Dist: loguru (==0.6.0)
Requires-Dist: markupsafe (==2.1.1)
Requires-Dist: p2pnetwork (==1.1)
Requires-Dist: packaging (==21.3)
Requires-Dist: pluggy (==1.0.0)
Requires-Dist: py (==1.11.0)
Requires-Dist: pycryptodome (==3.14.1)
Requires-Dist: pyparsing (==3.0.7)
Requires-Dist: pytest (==7.1.1)
Requires-Dist: pytest-asyncio (==0.18.2)
Requires-Dist: python-dotenv (==0.19.2)
Requires-Dist: requests (==2.27.1)
Requires-Dist: tomli (==2.0.1)
Requires-Dist: urllib3 (==1.26.9)
Requires-Dist: waitress (==2.1.1)
Requires-Dist: werkzeug (==2.0.3)
